argparse_to_json/__init__.py
argparse_to_json/converter.py
argparse_to_json-0.0.1.dist-info/LICENSE
argparse_to_json-0.0.1.dist-info/METADATA
argparse_to_json-0.0.1.dist-info/WHEEL
argparse_to_json-0.0.1.dist-info/top_level.txt
argparse_to_json-0.0.1.dist-info/RECORD
