Metadata-Version: 2.1
Name: argparse-to-json
Version: 0.0.1
Summary: Convert argparse.ArgumentParser to json compatible with JSON Form
Home-page: https://github.com/childsish/argparse-to-json
Author: Liam H. Childs
Author-email: liam.h.childs@gmail.com
License: UNKNOWN
Platform: UNKNOWN
License-File: LICENSE
